asimov/__init__.py
asimov/client.py
asimov/core.py
asimov/py.typed
asimov/resources/__init__.py
asimov/resources/add.py
asimov/resources/search.py
asimov_sdk-1.0.0.dist-info/licenses/LICENSE
asimov_sdk-1.0.0.dist-info/METADATA
asimov_sdk-1.0.0.dist-info/WHEEL
asimov_sdk-1.0.0.dist-info/top_level.txt
asimov_sdk-1.0.0.dist-info/RECORD
